vbt/__init__.py
vbt/cli.py
vbt/config.py
vbt/logger.py
vbt/utils.py
vbt/commands/__init__.py
vbt/commands/trim.py
video_batch_trim-0.1.0.dist-info/METADATA
video_batch_trim-0.1.0.dist-info/WHEEL
video_batch_trim-0.1.0.dist-info/entry_points.txt
video_batch_trim-0.1.0.dist-info/licenses/LICENSE
video_batch_trim-0.1.0.dist-info/RECORD
