Metadata-Version: 2.4
Name: video-batch-trim
Version: 0.1.0
Summary: 视频批量裁剪命令行工具 - 使用 ffmpeg 批量删除视频开头指定秒数
Project-URL: Homepage, https://github.com/yourusername/video-batch-trim
Project-URL: Documentation, https://github.com/yourusername/video-batch-trim#readme
Project-URL: Repository, https://github.com/yourusername/video-batch-trim
Project-URL: Issues, https://github.com/yourusername/video-batch-trim/issues
Author: VBT Developer
License: MIT
License-File: LICENSE
Keywords: batch,cli,command-line,ffmpeg,trim,video,video-processing
Classifier: Development Status :: 4 - Beta
Classifier: Intended Audience :: Developers
Classifier: Intended Audience :: End Users/Desktop
Classifier: License :: OSI Approved :: MIT License
Classifier: Operating System :: OS Independent
Classifier: Programming Language :: Python :: 3
Classifier: Programming Language :: Python :: 3.8
Classifier: Programming Language :: Python :: 3.9
Classifier: Programming Language :: Python :: 3.10
Classifier: Programming Language :: Python :: 3.11
Classifier: Programming Language :: Python :: 3.12
Classifier: Topic :: Multimedia :: Video
Classifier: Topic :: Utilities
Requires-Python: >=3.8
Requires-Dist: build>=1.2.2.post1
Requires-Dist: click>=8.0
Requires-Dist: loguru>=0.7.0
Requires-Dist: pyyaml>=6.0
Requires-Dist: setuptools>=75.3.3
Requires-Dist: tqdm>=4.65
